PyFlightSearch/QPX.py
PyFlightSearch/__init__.py
PyFlightSearch/flight.py
PyFlightSearch-0.2.0.dist-info/DESCRIPTION.rst
PyFlightSearch-0.2.0.dist-info/METADATA
PyFlightSearch-0.2.0.dist-info/RECORD
PyFlightSearch-0.2.0.dist-info/WHEEL
PyFlightSearch-0.2.0.dist-info/metadata.json
PyFlightSearch-0.2.0.dist-info/top_level.txt
