Metadata-Version: 2.0
Name: PyFlightSearch
Version: 0.2.0
Summary: Generate a Webpage using results from coala
Home-page: https://github.com/aerupt/PyFlightSearch
Author: Lasse Schuirmann
Author-email: lasse.schuirmann@gmail.com
License: MIT
Platform: any
Requires-Dist: attrs (~=16.3.0)
Requires-Dist: requests (~=2.12.4)
